easytype/__about__.py
easytype/__init__.py
easytype/common.py
easytype/core.py
easytype/utils.py
easytype-0.0.5.dist-info/METADATA
easytype-0.0.5.dist-info/WHEEL
easytype-0.0.5.dist-info/RECORD
